AUTHORS
CHANGELOG.txt
DESCRIPTION
LICENSE
MANIFEST.in
README.rst
setup.py
python_uptimerobot.egg-info/PKG-INFO
python_uptimerobot.egg-info/SOURCES.txt
python_uptimerobot.egg-info/dependency_links.txt
python_uptimerobot.egg-info/top_level.txt
uptimerobot/__init__.py
uptimerobot/uptimerobot.py