Metadata-Version: 1.1
Name: python-uptimerobot
Version: 0.1.5
Summary: Uptime Robot http://uptimerobot.com integration for your Python project. 
Home-page: https://github.com/arteria/python-uptimerobot
Author: arteria GmbH
Author-email: admin@arteria.ch
License: The MIT License
Keywords: uptime robot,API,monitoring
Platform: OS Independent
Classifier: Programming Language :: Python :: 2
Classifier: Programming Language :: Python :: 3
